[{"id": "213e438b17282904772446704d0b28", "image": ["E:\\天池比赛\\tianchi\\train\\images\\213e438b17282904772446704d0b28-0.jpg"], "output": "商品材质", "picture2text": ""},
{"id": "2104a80d17282572952783243d0afd", "image": ["E:\\天池比赛\\tianchi\\train\\images\\2104a80d17282572952783243d0afd-0.jpg"], "output": "商品材质", "picture2text": ""},
{"id": "212c8bd517276234453407314d1039", "image": ["E:\\天池比赛\\tianchi\\train\\images\\212c8bd517276234453407314d1039-0.jpg"], "output": "商品规格", "picture2text": ""},
{"id": "2166278d17280312481914032d1034", "image": ["E:\\天池比赛\\tianchi\\train\\images\\2166278d17280312481914032d1034-0.jpg"], "output": "排水方式", "picture2text": ""},
{"id": "21082e0317274845152512370d0a96", "image": ["E:\\天池比赛\\tianchi\\train\\images\\21082e0317274845152512370d0a96-0.jpg"], "output": "控制方式", "picture2text": ""},
{"id": "2107347617277435206931576d0af4", "image": ["E:\\天池比赛\\tianchi\\train\\images\\2107347617277435206931576d0af4-0.jpg"], "output": "是否易褪色", "picture2text": ""},
{"id": "216604b817280094815601716d0fb5", "image": ["E:\\天池比赛\\tianchi\\train\\images\\216604b817280094815601716d0fb5-0.jpg"], "output": "上市时间", "picture2text": ""},
{"id": "210895e617282707337795538d13de", "image": ["E:\\天池比赛\\tianchi\\train\\images\\210895e617282707337795538d13de-0.jpg"], "output": "是否会生锈", "picture2text": ""},
{"id": "21662e5617275750723646542d0b2d", "image": ["E:\\天池比赛\\tianchi\\train\\images\\21662e5617275750723646542d0b2d-0.jpg"], "output": "上市时间", "picture2text": ""},
{"id": "2132e5a717272236083744698d100c", "image": ["E:\\天池比赛\\tianchi\\train\\images\\2132e5a717272236083744698d100c-0.jpg"], "output": "是否会生锈", "picture2text": ""},
{"id": "213fd84e17280932546907457d0fcf", "image": ["E:\\天池比赛\\tianchi\\train\\images\\213fd84e17280932546907457d0fcf-0.jpg"], "output": "反馈用后症状", "picture2text": ""},
{"id": "213c7a7517275077264458242d0aa6", "image": ["E:\\天池比赛\\tianchi\\train\\images\\213c7a7517275077264458242d0aa6-0.jpg"], "output": "适用季节", "picture2text": ""},
{"id": "21509d6617281881109905429d1036", "image": ["E:\\天池比赛\\tianchi\\train\\images\\21509d6617281881109905429d1036-0.jpg"], "output": "何时上货", "picture2text": ""},
{"id": "2108af3917272709977973439d10c4", "image": ["E:\\天池比赛\\tianchi\\train\\images\\2108af3917272709977973439d10c4-0.jpg"], "output": "发货数量", "picture2text": ""},
{"id": "2150927317278613671596062d1039", "image": ["E:\\天池比赛\\tianchi\\train\\images\\2150927317278613671596062d1039-0.jpg"], "output": "功效功能", "picture2text": ""},
{"id": "21328ddd17280467974994592d0fc9", "image": ["E:\\天池比赛\\tianchi\\train\\images\\21328ddd17280467974994592d0fc9-0.jpg"], "output": "功效功能", "picture2text": ""},
{"id": "2108bb4317279151021748108d1071", "image": ["E:\\天池比赛\\tianchi\\train\\images\\2108bb4317279151021748108d1071-0.jpg"], "output": "商品规格", "picture2text": ""},
{"id": "2146944917274155359722397d0ff6", "image": ["E:\\天池比赛\\tianchi\\train\\images\\2146944917274155359722397d0ff6-0.jpg"], "output": "功效功能", "picture2text": ""},
{"id": "2133f8be17278843450867083d1020", "image": ["E:\\天池比赛\\tianchi\\train\\images\\2133f8be17278843450867083d1020-0.jpg"], "output": "套装推荐", "picture2text": ""},
{"id": "210402f617276449326898442d0af2", "image": ["E:\\天池比赛\\tianchi\\train\\images\\210402f617276449326898442d0af2-0.jpg"], "output": "商品规格", "picture2text": ""},
{"id": "21050f9717273255506944683d0fdd", "image": ["E:\\天池比赛\\tianchi\\train\\images\\21050f9717273255506944683d0fdd-0.jpg"], "output": "是否好用", "picture2text": ""},
{"id": "213ce7e817280091082137296d0ae5", "image": ["E:\\天池比赛\\tianchi\\train\\images\\213ce7e817280091082137296d0ae5-0.jpg"], "output": "是否易褪色", "picture2text": ""},
{"id": "2150aa6317274169996311376d0b11", "image": ["E:\\天池比赛\\tianchi\\train\\images\\2150aa6317274169996311376d0b11-0.jpg"], "output": "用法用量", "picture2text": ""},
{"id": "2146a76617275885114992755d0b2c", "image": ["E:\\天池比赛\\tianchi\\train\\images\\2146a76617275885114992755d0b2c-0.jpg", "E:\\天池比赛\\tianchi\\train\\images\\2146a76617275885114992755d0b2c-1.jpg"], "output": "上市时间", "picture2text": ""},
{"id": "213d025717273501863691819d0fcd", "image": ["E:\\天池比赛\\tianchi\\train\\images\\213d025717273501863691819d0fcd-0.jpg"], "output": "用法用量", "picture2text": ""},
{"id": "212c150417277857487232070d1045", "image": ["E:\\天池比赛\\tianchi\\train\\images\\212c150417277857487232070d1045-0.jpg"], "output": "套装推荐", "picture2text": ""},
{"id": "213e97a017276141281136851d0fe5", "image": ["E:\\天池比赛\\tianchi\\train\\images\\213e97a017276141281136851d0fe5-0.jpg"], "output": "包装区别", "picture2text": ""},
{"id": "21056b7e17277524856454060d0aee", "image": ["E:\\天池比赛\\tianchi\\train\\images\\21056b7e17277524856454060d0aee-0.jpg"], "output": "用法用量", "picture2text": ""},
{"id": "21313f8417274787972381149d1036", "image": ["E:\\天池比赛\\tianchi\\train\\images\\21313f8417274787972381149d1036-0.jpg"], "output": "能否调光", "picture2text": ""},
{"id": "2108bb4317274127970466765d1071", "image": ["E:\\天池比赛\\tianchi\\train\\images\\2108bb4317274127970466765d1071-0.jpg"], "output": "用法用量", "picture2text": ""},
{"id": "21312fc217281320098786988d100f", "image": ["E:\\天池比赛\\tianchi\\train\\images\\21312fc217281320098786988d100f-0.jpg"], "output": "排水方式", "picture2text": ""},
{"id": "212ca02217282625753515572d1018", "image": ["E:\\天池比赛\\tianchi\\train\\images\\212ca02217282625753515572d1018-0.jpg"], "output": "单品推荐", "picture2text": ""},
{"id": "212bc81d17276539241035368d0b0b", "image": ["E:\\天池比赛\\tianchi\\train\\images\\212bc81d17276539241035368d0b0b-0.jpg", "E:\\天池比赛\\tianchi\\train\\images\\212bc81d17276539241035368d0b0b-1.jpg"], "output": "版本款型区别", "picture2text": ""},
{"id": "21329d1e17276023516477393d0fa2", "image": ["E:\\天池比赛\\tianchi\\train\\images\\21329d1e17276023516477393d0fa2-0.jpg"], "output": "包装区别", "picture2text": ""},
{"id": "21054e4a17281345516455057d1038", "image": ["E:\\天池比赛\\tianchi\\train\\images\\21054e4a17281345516455057d1038-0.jpg"], "output": "排水方式", "picture2text": ""},
{"id": "2133765617278739480824545d0fbc", "image": ["E:\\天池比赛\\tianchi\\train\\images\\2133765617278739480824545d0fbc-0.jpg"], "output": "商品规格", "picture2text": ""},
{"id": "212b956c17282134923653071d0faf", "image": ["E:\\天池比赛\\tianchi\\train\\images\\212b956c17282134923653071d0faf-0.jpg"], "output": "适用季节", "picture2text": ""},
{"id": "212cd60617272683081188339d0fde", "image": ["E:\\天池比赛\\tianchi\\train\\images\\212cd60617272683081188339d0fde-0.jpg"], "output": "功效功能", "picture2text": ""},
{"id": "2104645517279124834662449d1011", "image": ["E:\\天池比赛\\tianchi\\train\\images\\2104645517279124834662449d1011-0.jpg"], "output": "何时上货", "picture2text": ""},
{"id": "2103c49217279299519572616d0b0d", "image": ["E:\\天池比赛\\tianchi\\train\\images\\2103c49217279299519572616d0b0d-0.jpg"], "output": "包装区别", "picture2text": ""},
{"id": "2167080c17273607920326399d104e", "image": ["E:\\天池比赛\\tianchi\\train\\images\\2167080c17273607920326399d104e-0.jpg"], "output": "单品推荐", "picture2text": ""},
{"id": "21077ee817281392804181945d0b15", "image": ["E:\\天池比赛\\tianchi\\train\\images\\21077ee817281392804181945d0b15-0.jpg"], "output": "是否易褪色", "picture2text": ""},
{"id": "2104a7ff17273327826631393d1056", "image": ["E:\\天池比赛\\tianchi\\train\\images\\2104a7ff17273327826631393d1056-0.jpg"], "output": "套装推荐", "picture2text": ""},
{"id": "2166fb3f17274298400723919d0ae0", "image": ["E:\\天池比赛\\tianchi\\train\\images\\2166fb3f17274298400723919d0ae0-0.jpg"], "output": "能否调光", "picture2text": ""},
{"id": "21663e5317280326575273428d1011", "image": ["E:\\天池比赛\\tianchi\\train\\images\\21663e5317280326575273428d1011-0.jpg"], "output": "反馈密封性不好", "picture2text": ""},
{"id": "212be38d17280067962783918d0fd6", "image": ["E:\\天池比赛\\tianchi\\train\\images\\212be38d17280067962783918d0fd6-0.jpg"], "output": "包装区别", "picture2text": ""},
{"id": "2167646217280512321968524d0ffd", "image": ["E:\\天池比赛\\tianchi\\train\\images\\2167646217280512321968524d0ffd-0.jpg"], "output": "控制方式", "picture2text": ""},
{"id": "21049e3617282802019842517d0fbf", "image": ["E:\\天池比赛\\tianchi\\train\\images\\21049e3617282802019842517d0fbf-0.jpg"], "output": "套装推荐", "picture2text": ""},
{"id": "2150394017276873677027343d0b24", "image": ["E:\\天池比赛\\tianchi\\train\\images\\2150394017276873677027343d0b24-0.jpg"], "output": "用法用量", "picture2text": ""},
{"id": "213dbbe517278865952913592d0b10", "image": ["E:\\天池比赛\\tianchi\\train\\images\\213dbbe517278865952913592d0b10-0.jpg"], "output": "是否好用", "picture2text": ""},
{"id": "0b51028517272402945787231d0f3a", "image": ["E:\\天池比赛\\tianchi\\train\\images\\0b51028517272402945787231d0f3a-0.jpg"], "output": "发货数量", "picture2text": ""},
{"id": "2108b0bc17279155226222784d0fc6", "image": ["E:\\天池比赛\\tianchi\\train\\images\\2108b0bc17279155226222784d0fc6-0.jpg", "E:\\天池比赛\\tianchi\\train\\images\\2108b0bc17279155226222784d0fc6-1.jpg"], "output": "版本款型区别", "picture2text": ""},
{"id": "213dfe0617281054782153484d0f8a", "image": ["E:\\天池比赛\\tianchi\\train\\images\\213dfe0617281054782153484d0f8a-0.jpg"], "output": "单品推荐", "picture2text": ""},
{"id": "2106c60d17281705283675304d101f", "image": ["E:\\天池比赛\\tianchi\\train\\images\\2106c60d17281705283675304d101f-0.jpg"], "output": "发货数量", "picture2text": ""},
{"id": "213f620917282967967126719d1005", "image": ["E:\\天池比赛\\tianchi\\train\\images\\213f620917282967967126719d1005-0.jpg"], "output": "是否好用", "picture2text": ""},
{"id": "213c7ca017279631957936148d0f81", "image": ["E:\\天池比赛\\tianchi\\train\\images\\213c7ca017279631957936148d0f81-0.jpg"], "output": "套装推荐", "picture2text": ""},
{"id": "2150b4c117279258245817890d0a27", "image": ["E:\\天池比赛\\tianchi\\train\\images\\2150b4c117279258245817890d0a27-0.jpg"], "output": "气泡", "picture2text": ""},
{"id": "213df65217276551096714498d1024", "image": ["E:\\天池比赛\\tianchi\\train\\images\\213df65217276551096714498d1024-0.jpg"], "output": "功效功能", "picture2text": ""},
{"id": "2127d37217274090272916770d100f", "image": ["E:\\天池比赛\\tianchi\\train\\images\\2127d37217274090272916770d100f-0.jpg"], "output": "用法用量", "picture2text": ""},
{"id": "213d6abb17278450739701377d10d8", "image": ["E:\\天池比赛\\tianchi\\train\\images\\213d6abb17278450739701377d10d8-0.jpg"], "output": "功效功能", "picture2text": ""},
{"id": "2166ed8d17279194437286473d0fe3", "image": ["E:\\天池比赛\\tianchi\\train\\images\\2166ed8d17279194437286473d0fe3-0.jpg"], "output": "控制方式", "picture2text": ""},
{"id": "21077f1817272305779762234d0af7", "image": ["E:\\天池比赛\\tianchi\\train\\images\\21077f1817272305779762234d0af7-0.jpg"], "output": "何时上货", "picture2text": ""},
{"id": "213c4c8017279190646104809d1056", "image": ["E:\\天池比赛\\tianchi\\train\\images\\213c4c8017279190646104809d1056-0.jpg"], "output": "商品材质", "picture2text": ""},
{"id": "212c584817279507019694403d0fce", "image": ["E:\\天池比赛\\tianchi\\train\\images\\212c584817279507019694403d0fce-0.jpg"], "output": "能否调光", "picture2text": ""},
{"id": "213e5c9d17283166324026775d0fd4", "image": ["E:\\天池比赛\\tianchi\\train\\images\\213e5c9d17283166324026775d0fd4-0.jpg"], "output": "用法用量", "picture2text": ""},
{"id": "2108651517279621921498328d100d", "image": ["E:\\天池比赛\\tianchi\\train\\images\\2108651517279621921498328d100d-0.jpg", "E:\\天池比赛\\tianchi\\train\\images\\2108651517279621921498328d100d-1.jpg"], "output": "包装区别", "picture2text": ""},
{"id": "2167520017272624992884514d0b35", "image": ["E:\\天池比赛\\tianchi\\train\\images\\2167520017272624992884514d0b35-0.jpg"], "output": "气泡", "picture2text": ""},
{"id": "2135e2c217273563615331873d0f80", "image": ["E:\\天池比赛\\tianchi\\train\\images\\2135e2c217273563615331873d0f80-0.jpg"], "output": "上市时间", "picture2text": ""},
{"id": "2133672c17279661881117382d1032", "image": ["E:\\天池比赛\\tianchi\\train\\images\\2133672c17279661881117382d1032-0.jpg"], "output": "功效功能", "picture2text": ""},
{"id": "212b943017277925174498038d1025", "image": ["E:\\天池比赛\\tianchi\\train\\images\\212b943017277925174498038d1025-0.jpg"], "output": "控制方式", "picture2text": ""},
{"id": "213ee7f117275165747167671d0fee", "image": ["E:\\天池比赛\\tianchi\\train\\images\\213ee7f117275165747167671d0fee-0.jpg", "E:\\天池比赛\\tianchi\\train\\images\\213ee7f117275165747167671d0fee-1.jpg"], "output": "是否好用", "picture2text": ""},
{"id": "2104491517282052128886267d0f9a", "image": ["E:\\天池比赛\\tianchi\\train\\images\\2104491517282052128886267d0f9a-0.jpg"], "output": "养护方法", "picture2text": ""},
{"id": "2167646217275685663348278d0ffd", "image": ["E:\\天池比赛\\tianchi\\train\\images\\2167646217275685663348278d0ffd-0.jpg"], "output": "版本款型区别", "picture2text": ""},
{"id": "0bf8d14017273156763468377d0f98", "image": ["E:\\天池比赛\\tianchi\\train\\images\\0bf8d14017273156763468377d0f98-0.jpg"], "output": "反馈密封性不好", "picture2text": ""},
{"id": "212b7c9217273350224882194d0a98", "image": ["E:\\天池比赛\\tianchi\\train\\images\\212b7c9217273350224882194d0a98-0.jpg"], "output": "上市时间", "picture2text": ""},
{"id": "213f62bd17272633296844344d0ff1", "image": ["E:\\天池比赛\\tianchi\\train\\images\\213f62bd17272633296844344d0ff1-0.jpg"], "output": "商品规格", "picture2text": ""},
{"id": "21074a7717275661958963958d103e", "image": ["E:\\天池比赛\\tianchi\\train\\images\\21074a7717275661958963958d103e-0.jpg"], "output": "套装推荐", "picture2text": ""},
{"id": "2166fb3f17280943917662302d0ae0", "image": ["E:\\天池比赛\\tianchi\\train\\images\\2166fb3f17280943917662302d0ae0-0.jpg"], "output": "上市时间", "picture2text": ""},
{"id": "2136487a17272243343246549d0a31", "image": ["E:\\天池比赛\\tianchi\\train\\images\\2136487a17272243343246549d0a31-0.jpg"], "output": "反馈密封性不好", "picture2text": ""},
{"id": "0bf8c4fc17276642165814398d0a5d", "image": ["E:\\天池比赛\\tianchi\\train\\images\\0bf8c4fc17276642165814398d0a5d-0.jpg"], "output": "上市时间", "picture2text": ""},
{"id": "0b59b53717272701902836613d0ad0", "image": ["E:\\天池比赛\\tianchi\\train\\images\\0b59b53717272701902836613d0ad0-0.jpg", "E:\\天池比赛\\tianchi\\train\\images\\0b59b53717272701902836613d0ad0-1.jpg", "E:\\天池比赛\\tianchi\\train\\images\\0b59b53717272701902836613d0ad0-2.jpg"], "output": "反馈密封性不好", "picture2text": ""},
{"id": "212c98da17275795776537634d100f", "image": ["E:\\天池比赛\\tianchi\\train\\images\\212c98da17275795776537634d100f-0.jpg", "E:\\天池比赛\\tianchi\\train\\images\\212c98da17275795776537634d100f-1.jpg", "E:\\天池比赛\\tianchi\\train\\images\\212c98da17275795776537634d100f-2.jpg", "E:\\天池比赛\\tianchi\\train\\images\\212c98da17275795776537634d100f-3.jpg"], "output": "反馈密封性不好", "picture2text": ""},
{"id": "212797d117273571702575494d0acd", "image": ["E:\\天池比赛\\tianchi\\train\\images\\212797d117273571702575494d0acd-0.jpg"], "output": "商品材质", "picture2text": ""},
{"id": "213ef6a617280879509142324d0b7c", "image": ["E:\\天池比赛\\tianchi\\train\\images\\213ef6a617280879509142324d0b7c-0.jpg"], "output": "版本款型区别", "picture2text": ""},
{"id": "2154753a17275943226896102d10d7", "image": ["E:\\天池比赛\\tianchi\\train\\images\\2154753a17275943226896102d10d7-0.jpg"], "output": "控制方式", "picture2text": ""},
{"id": "213dfabd17277721534497218d1099", "image": ["E:\\天池比赛\\tianchi\\train\\images\\213dfabd17277721534497218d1099-0.jpg"], "output": "适用季节", "picture2text": ""},
{"id": "2146b5c517273287182141021d0af0", "image": ["E:\\天池比赛\\tianchi\\train\\images\\2146b5c517273287182141021d0af0-0.jpg"], "output": "排水方式", "picture2text": ""},
{"id": "213cf9f417278413865917993d0f77", "image": ["E:\\天池比赛\\tianchi\\train\\images\\213cf9f417278413865917993d0f77-0.jpg"], "output": "何时上货", "picture2text": ""},
{"id": "212b14da17281748234545696d0add", "image": [], "output": "何时上货", "picture2text": ""},
{"id": "2127d70417282883380917522d0a8f", "image": ["E:\\天池比赛\\tianchi\\train\\images\\2127d70417282883380917522d0a8f-0.jpg"], "output": "套装推荐", "picture2text": ""},
{"id": "2133eecd17276689006337850d0fc0", "image": ["E:\\天池比赛\\tianchi\\train\\images\\2133eecd17276689006337850d0fc0-0.jpg"], "output": "何时上货", "picture2text": ""},
{"id": "212c0cf517272582004521753d100f", "image": ["E:\\天池比赛\\tianchi\\train\\images\\212c0cf517272582004521753d100f-0.jpg"], "output": "气泡", "picture2text": ""},
{"id": "2133f8be17279627305965388d1020", "image": ["E:\\天池比赛\\tianchi\\train\\images\\2133f8be17279627305965388d1020-0.jpg"], "output": "单品推荐", "picture2text": ""},
{"id": "212cadea17279258569975439d1028", "image": ["E:\\天池比赛\\tianchi\\train\\images\\212cadea17279258569975439d1028-0.jpg"], "output": "功效功能", "picture2text": ""},
{"id": "213ca40d17272374184656512d1034", "image": ["E:\\天池比赛\\tianchi\\train\\images\\213ca40d17272374184656512d1034-0.jpg"], "output": "气泡", "picture2text": ""},
{"id": "21074d6b17273969859158097d103f", "image": ["E:\\天池比赛\\tianchi\\train\\images\\21074d6b17273969859158097d103f-0.jpg", "E:\\天池比赛\\tianchi\\train\\images\\21074d6b17273969859158097d103f-1.jpg"], "output": "发货数量", "picture2text": ""},
{"id": "212a804e17279148297254210d102f", "image": ["E:\\天池比赛\\tianchi\\train\\images\\212a804e17279148297254210d102f-0.jpg"], "output": "信号情况", "picture2text": ""},
{"id": "21049d9917282032863412958d103f", "image": ["E:\\天池比赛\\tianchi\\train\\images\\21049d9917282032863412958d103f-0.jpg"], "output": "信号情况", "picture2text": ""},
{"id": "212789ae17277670537991004d0fd7", "image": ["E:\\天池比赛\\tianchi\\train\\images\\212789ae17277670537991004d0fd7-0.jpg"], "output": "能否调光", "picture2text": ""},
{"id": "2108691417277688676983959d0ff9", "image": ["E:\\天池比赛\\tianchi\\train\\images\\2108691417277688676983959d0ff9-0.jpg"], "output": "单品推荐", "picture2text": ""},
{"id": "213dd80c17277658124558984d0fd2", "image": ["E:\\天池比赛\\tianchi\\train\\images\\213dd80c17277658124558984d0fd2-0.jpg"], "output": "功效功能", "picture2text": ""},
{"id": "213fb61517280375869288342d0b1b", "image": ["E:\\天池比赛\\tianchi\\train\\images\\213fb61517280375869288342d0b1b-0.jpg"], "output": "适用季节", "picture2text": ""},
{"id": "2104a6e317278040738596255d1041", "image": ["E:\\天池比赛\\tianchi\\train\\images\\2104a6e317278040738596255d1041-0.jpg"], "output": "单品推荐", "picture2text": ""},
{"id": "212cefab17274133646458141d104a", "image": ["E:\\天池比赛\\tianchi\\train\\images\\212cefab17274133646458141d104a-0.jpg"], "output": "适用季节", "picture2text": ""},
{"id": "0b5e135717281430940456867d0f9d", "image": ["E:\\天池比赛\\tianchi\\train\\images\\0b5e135717281430940456867d0f9d-0.jpg"], "output": "适用季节", "picture2text": ""},
{"id": "2131049117280287118221372d0b8d", "image": ["E:\\天池比赛\\tianchi\\train\\images\\2131049117280287118221372d0b8d-0.jpg"], "output": "单品推荐", "picture2text": ""},
{"id": "213f4ce117273103408518797d598c", "image": ["E:\\天池比赛\\tianchi\\train\\images\\213f4ce117273103408518797d598c-0.png"], "output": "商品规格", "picture2text": ""},
{"id": "2166e8da17274361916861415d1051", "image": ["E:\\天池比赛\\tianchi\\train\\images\\2166e8da17274361916861415d1051-0.jpg"], "output": "套装推荐", "picture2text": ""},
{"id": "2150bf3317276759583287266d0b00", "image": ["E:\\天池比赛\\tianchi\\train\\images\\2150bf3317276759583287266d0b00-0.jpg"], "output": "反馈用后症状", "picture2text": ""},
{"id": "21080af017277891648135916d1007", "image": ["E:\\天池比赛\\tianchi\\train\\images\\21080af017277891648135916d1007-0.jpg"], "output": "气泡", "picture2text": ""},
{"id": "212c0ddb17282641946906576d1049", "image": ["E:\\天池比赛\\tianchi\\train\\images\\212c0ddb17282641946906576d1049-0.jpg"], "output": "包装区别", "picture2text": ""},
{"id": "212c5b2e17276183422897200d0b24", "image": ["E:\\天池比赛\\tianchi\\train\\images\\212c5b2e17276183422897200d0b24-0.jpg"], "output": "排水方式", "picture2text": ""},
{"id": "2132901e17280176158325454d0af0", "image": ["E:\\天池比赛\\tianchi\\train\\images\\2132901e17280176158325454d0af0-0.jpg", "E:\\天池比赛\\tianchi\\train\\images\\2132901e17280176158325454d0af0-1.jpg"], "output": "套装推荐", "picture2text": ""},
{"id": "2167595d17277786417642566d1025", "image": ["E:\\天池比赛\\tianchi\\train\\images\\2167595d17277786417642566d1025-0.jpg"], "output": "版本款型区别", "picture2text": ""},
{"id": "0bbb343917279635414337036d0f91", "image": ["E:\\天池比赛\\tianchi\\train\\images\\0bbb343917279635414337036d0f91-0.jpg"], "output": "何时上货", "picture2text": ""},
{"id": "0bf8ecdd17281156773881109d0fbf", "image": ["E:\\天池比赛\\tianchi\\train\\images\\0bf8ecdd17281156773881109d0fbf-0.jpg"], "output": "发货数量", "picture2text": ""},
{"id": "212b7c9217273957841493085d0a98", "image": ["E:\\天池比赛\\tianchi\\train\\images\\212b7c9217273957841493085d0a98-0.jpg"], "output": "反馈密封性不好", "picture2text": ""},
{"id": "213fcf9717275050226962158d1002", "image": ["E:\\天池比赛\\tianchi\\train\\images\\213fcf9717275050226962158d1002-0.png", "E:\\天池比赛\\tianchi\\train\\images\\213fcf9717275050226962158d1002-1.png"], "output": "适用季节", "picture2text": ""},
{"id": "213ea62917276731372422389d0b1f", "image": ["E:\\天池比赛\\tianchi\\train\\images\\213ea62917276731372422389d0b1f-0.jpg", "E:\\天池比赛\\tianchi\\train\\images\\213ea62917276731372422389d0b1f-1.jpg", "E:\\天池比赛\\tianchi\\train\\images\\213ea62917276731372422389d0b1f-2.jpg"], "output": "单品推荐", "picture2text": ""},
{"id": "2150aa6317272313435904916d0b11", "image": ["E:\\天池比赛\\tianchi\\train\\images\\2150aa6317272313435904916d0b11-0.jpg"], "output": "包装区别", "picture2text": ""},
{"id": "2166827317279603843896107d1028", "image": ["E:\\天池比赛\\tianchi\\train\\images\\2166827317279603843896107d1028-0.jpg"], "output": "功效功能", "picture2text": ""},
{"id": "2166278817273505728677418d0f86", "image": ["E:\\天池比赛\\tianchi\\train\\images\\2166278817273505728677418d0f86-0.jpg"], "output": "单品推荐", "picture2text": ""},
{"id": "0b5106f517273970950313142d0f90", "image": ["E:\\天池比赛\\tianchi\\train\\images\\0b5106f517273970950313142d0f90-0.jpg"], "output": "反馈用后症状", "picture2text": ""},
{"id": "213609f617277418434967321d0a5c", "image": ["E:\\天池比赛\\tianchi\\train\\images\\213609f617277418434967321d0a5c-0.jpg"], "output": "信号情况", "picture2text": ""},
{"id": "213d379717283064440913543d0f9a", "image": ["E:\\天池比赛\\tianchi\\train\\images\\213d379717283064440913543d0f9a-0.jpg"], "output": "是否会生锈", "picture2text": ""},
{"id": "213e983217275999569522312d0ad5", "image": ["E:\\天池比赛\\tianchi\\train\\images\\213e983217275999569522312d0ad5-0.jpg", "E:\\天池比赛\\tianchi\\train\\images\\213e983217275999569522312d0ad5-1.jpg"], "output": "何时上货", "picture2text": ""},
{"id": "210786b117281020388898414d0ae1", "image": ["E:\\天池比赛\\tianchi\\train\\images\\210786b117281020388898414d0ae1-0.jpg"], "output": "适用季节", "picture2text": ""},
{"id": "213d709f17272692345073536d0b06", "image": ["E:\\天池比赛\\tianchi\\train\\images\\213d709f17272692345073536d0b06-0.jpg"], "output": "商品材质", "picture2text": ""},
{"id": "21043ab017281199805422566d0a8f", "image": ["E:\\天池比赛\\tianchi\\train\\images\\21043ab017281199805422566d0a8f-0.jpg"], "output": "是否会生锈", "picture2text": ""},
{"id": "21056dce17278548387424123d0aef", "image": ["E:\\天池比赛\\tianchi\\train\\images\\21056dce17278548387424123d0aef-0.jpg"], "output": "单品推荐", "picture2text": ""},
{"id": "210536aa17275314711306795d0fcc", "image": ["E:\\天池比赛\\tianchi\\train\\images\\210536aa17275314711306795d0fcc-0.jpg"], "output": "版本款型区别", "picture2text": ""},
{"id": "2132d75117275313129547868d1014", "image": ["E:\\天池比赛\\tianchi\\train\\images\\2132d75117275313129547868d1014-0.jpg"], "output": "反馈密封性不好", "picture2text": ""},
{"id": "2132d8ed17277572141215273d0f57", "image": ["E:\\天池比赛\\tianchi\\train\\images\\2132d8ed17277572141215273d0f57-0.jpg"], "output": "发货数量", "picture2text": ""},
{"id": "2154606e17276278140924117d102f", "image": ["E:\\天池比赛\\tianchi\\train\\images\\2154606e17276278140924117d102f-0.jpg", "E:\\天池比赛\\tianchi\\train\\images\\2154606e17276278140924117d102f-1.jpg"], "output": "何时上货", "picture2text": ""},
{"id": "213656ed17273421371971964d1043", "image": ["E:\\天池比赛\\tianchi\\train\\images\\213656ed17273421371971964d1043-0.jpg"], "output": "单品推荐", "picture2text": ""},
{"id": "212cb60217282158707088586d100d", "image": ["E:\\天池比赛\\tianchi\\train\\images\\212cb60217282158707088586d100d-0.jpg", "E:\\天池比赛\\tianchi\\train\\images\\212cb60217282158707088586d100d-1.jpg"], "output": "用法用量", "picture2text": ""},
{"id": "2127dcb817282549835702803d0a87", "image": ["E:\\天池比赛\\tianchi\\train\\images\\2127dcb817282549835702803d0a87-0.jpg"], "output": "是否好用", "picture2text": ""},
{"id": "2107a79417280142673321068d0a74", "image": ["E:\\天池比赛\\tianchi\\train\\images\\2107a79417280142673321068d0a74-0.jpg"], "output": "控制方式", "picture2text": ""},
{"id": "213ee9da17272809215763090d0b14", "image": ["E:\\天池比赛\\tianchi\\train\\images\\213ee9da17272809215763090d0b14-0.jpg"], "output": "包装区别", "picture2text": ""},
{"id": "2127972817283008748108770d0af0", "image": ["E:\\天池比赛\\tianchi\\train\\images\\2127972817283008748108770d0af0-0.jpg"], "output": "是否好用", "picture2text": ""},
{"id": "210476d717276701910895898d0b0a", "image": ["E:\\天池比赛\\tianchi\\train\\images\\210476d717276701910895898d0b0a-0.jpg"], "output": "信号情况", "picture2text": ""},
{"id": "0b51100717272778324591916d0f93", "image": ["E:\\天池比赛\\tianchi\\train\\images\\0b51100717272778324591916d0f93-0.jpg"], "output": "套装推荐", "picture2text": ""},
{"id": "2108bd4617280036406031294d0b20", "image": ["E:\\天池比赛\\tianchi\\train\\images\\2108bd4617280036406031294d0b20-0.jpg"], "output": "适用季节", "picture2text": ""},
{"id": "21361c2a17281247457488872d102a", "image": ["E:\\天池比赛\\tianchi\\train\\images\\21361c2a17281247457488872d102a-0.jpg"], "output": "发货数量", "picture2text": ""},
{"id": "212b5a6f17276987722735364d0a70", "image": ["E:\\天池比赛\\tianchi\\train\\images\\212b5a6f17276987722735364d0a70-0.jpg"], "output": "能否调光", "picture2text": ""},
{"id": "2166c1d917273581051323901d0b27", "image": ["E:\\天池比赛\\tianchi\\train\\images\\2166c1d917273581051323901d0b27-0.jpg"], "output": "套装推荐", "picture2text": ""},
{"id": "216604cf17277397592341521d1033", "image": ["E:\\天池比赛\\tianchi\\train\\images\\216604cf17277397592341521d1033-0.jpg"], "output": "功效功能", "picture2text": ""},
{"id": "2135e2c217281996030893406d0f80", "image": ["E:\\天池比赛\\tianchi\\train\\images\\2135e2c217281996030893406d0f80-0.jpg"], "output": "能否调光", "picture2text": ""},
{"id": "213e438b17277679390631039d0b28", "image": ["E:\\天池比赛\\tianchi\\train\\images\\213e438b17277679390631039d0b28-0.jpg"], "output": "是否会生锈", "picture2text": ""},
{"id": "0be379e417278425524112948d13ab", "image": ["E:\\天池比赛\\tianchi\\train\\images\\0be379e417278425524112948d13ab-0.jpg"], "output": "功效功能", "picture2text": ""},
{"id": "2133d1e417276170549727544d0ff7", "image": ["E:\\天池比赛\\tianchi\\train\\images\\2133d1e417276170549727544d0ff7-0.jpg"], "output": "适用季节", "picture2text": ""},
{"id": "0b5dce3b17277072678493789d0f79", "image": ["E:\\天池比赛\\tianchi\\train\\images\\0b5dce3b17277072678493789d0f79-0.jpg", "E:\\天池比赛\\tianchi\\train\\images\\0b5dce3b17277072678493789d0f79-1.jpg"], "output": "气泡", "picture2text": ""},
{"id": "2108b7a917280285113556075d0b15", "image": ["E:\\天池比赛\\tianchi\\train\\images\\2108b7a917280285113556075d0b15-0.jpg"], "output": "功效功能", "picture2text": ""},
{"id": "2108af3917282788022877697d10c4", "image": ["E:\\天池比赛\\tianchi\\train\\images\\2108af3917282788022877697d10c4-0.jpg"], "output": "反馈密封性不好", "picture2text": ""},
{"id": "0b5180dd17276072755701138d100d", "image": ["E:\\天池比赛\\tianchi\\train\\images\\0b5180dd17276072755701138d100d-0.jpg"], "output": "控制方式", "picture2text": ""},
{"id": "2133d51a17273386515127050d1038", "image": ["E:\\天池比赛\\tianchi\\train\\images\\2133d51a17273386515127050d1038-0.jpg"], "output": "商品规格", "picture2text": ""},
{"id": "213cb92517275294114965892d0a9f", "image": ["E:\\天池比赛\\tianchi\\train\\images\\213cb92517275294114965892d0a9f-0.jpg"], "output": "适用季节", "picture2text": ""},
{"id": "213d946b17282000277591449d0fc8", "image": ["E:\\天池比赛\\tianchi\\train\\images\\213d946b17282000277591449d0fc8-0.jpg"], "output": "控制方式", "picture2text": ""},
{"id": "2107407a17279647647132925d0f78", "image": ["E:\\天池比赛\\tianchi\\train\\images\\2107407a17279647647132925d0f78-0.jpg"], "output": "适用季节", "picture2text": ""},
{"id": "2132d7f217279259584175905d1036", "image": ["E:\\天池比赛\\tianchi\\train\\images\\2132d7f217279259584175905d1036-0.jpg"], "output": "商品规格", "picture2text": ""},
{"id": "212b02d817273655939695165d0fad", "image": ["E:\\天池比赛\\tianchi\\train\\images\\212b02d817273655939695165d0fad-0.jpg"], "output": "控制方式", "picture2text": ""},
{"id": "21508da117278628620222990d1036", "image": ["E:\\天池比赛\\tianchi\\train\\images\\21508da117278628620222990d1036-0.jpg"], "output": "养护方法", "picture2text": ""},
{"id": "0bf8fbfd17281836378208571d0ad8", "image": ["E:\\天池比赛\\tianchi\\train\\images\\0bf8fbfd17281836378208571d0ad8-0.jpg"], "output": "养护方法", "picture2text": ""},
{"id": "21669c8917282996329695110d0b13", "image": ["E:\\天池比赛\\tianchi\\train\\images\\21669c8917282996329695110d0b13-0.jpg"], "output": "信号情况", "picture2text": ""},
{"id": "0b5120d117280620172677970d0ad7", "image": ["E:\\天池比赛\\tianchi\\train\\images\\0b5120d117280620172677970d0ad7-0.jpg"], "output": "功效功能", "picture2text": ""},
{"id": "21049d9917276126141516340d103f", "image": ["E:\\天池比赛\\tianchi\\train\\images\\21049d9917276126141516340d103f-0.jpg"], "output": "适用季节", "picture2text": ""},
{"id": "212b123517280458320668119d0b23", "image": ["E:\\天池比赛\\tianchi\\train\\images\\212b123517280458320668119d0b23-0.jpg"], "output": "发货数量", "picture2text": ""},
{"id": "2107a90717280590659603804d1033", "image": ["E:\\天池比赛\\tianchi\\train\\images\\2107a90717280590659603804d1033-0.jpg"], "output": "信号情况", "picture2text": ""},
{"id": "2166322017279405606825694d0b1e", "image": ["E:\\天池比赛\\tianchi\\train\\images\\2166322017279405606825694d0b1e-0.jpg"], "output": "单品推荐", "picture2text": ""},
{"id": "213624b217275032277666813d0f9e", "image": ["E:\\天池比赛\\tianchi\\train\\images\\213624b217275032277666813d0f9e-0.jpg"], "output": "反馈密封性不好", "picture2text": ""},
{"id": "213f291a17279678810608584d0fb8", "image": ["E:\\天池比赛\\tianchi\\train\\images\\213f291a17279678810608584d0fb8-0.jpg"], "output": "发货数量", "picture2text": ""},
{"id": "212bbff317276740590923636d0ff9", "image": ["E:\\天池比赛\\tianchi\\train\\images\\212bbff317276740590923636d0ff9-0.jpg"], "output": "包装区别", "picture2text": ""},
{"id": "2127bcd917278512960541512d0fe9", "image": ["E:\\天池比赛\\tianchi\\train\\images\\2127bcd917278512960541512d0fe9-0.jpg"], "output": "养护方法", "picture2text": ""},
{"id": "213c7d8e17277665858002955d0faf", "image": ["E:\\天池比赛\\tianchi\\train\\images\\213c7d8e17277665858002955d0faf-0.jpg"], "output": "发货数量", "picture2text": ""},
{"id": "0b51dfbb17277070734367651d0ae1", "image": ["E:\\天池比赛\\tianchi\\train\\images\\0b51dfbb17277070734367651d0ae1-0.png"], "output": "商品材质", "picture2text": ""},
{"id": "212c86dc17272752834995248d105c", "image": ["E:\\天池比赛\\tianchi\\train\\images\\212c86dc17272752834995248d105c-0.jpg"], "output": "是否好用", "picture2text": ""},
{"id": "213dba3a17279417381448033d0a3a", "image": ["E:\\天池比赛\\tianchi\\train\\images\\213dba3a17279417381448033d0a3a-0.jpg"], "output": "反馈密封性不好", "picture2text": ""},
{"id": "213cb92517273433087797085d0a9f", "image": ["E:\\天池比赛\\tianchi\\train\\images\\213cb92517273433087797085d0a9f-0.jpg"], "output": "套装推荐", "picture2text": ""},
{"id": "213fe4a617281337227462124d0ada", "image": ["E:\\天池比赛\\tianchi\\train\\images\\213fe4a617281337227462124d0ada-0.jpg"], "output": "适用季节", "picture2text": ""},
{"id": "212ccb5917282965269817932d13fb", "image": ["E:\\天池比赛\\tianchi\\train\\images\\212ccb5917282965269817932d13fb-0.jpg"], "output": "排水方式", "picture2text": ""},
{"id": "213c7f8217272559177153838d0f72", "image": ["E:\\天池比赛\\tianchi\\train\\images\\213c7f8217272559177153838d0f72-0.jpg"], "output": "用法用量", "picture2text": ""},
{"id": "210448bd17278310463885155d0fef", "image": ["E:\\天池比赛\\tianchi\\train\\images\\210448bd17278310463885155d0fef-0.jpg"], "output": "用法用量", "picture2text": ""},
{"id": "215091ca17275195440614365d1017", "image": ["E:\\天池比赛\\tianchi\\train\\images\\215091ca17275195440614365d1017-0.jpg"], "output": "气泡", "picture2text": ""},
{"id": "212c0cf517282637482661905d100f", "image": ["E:\\天池比赛\\tianchi\\train\\images\\212c0cf517282637482661905d100f-0.jpg", "E:\\天池比赛\\tianchi\\train\\images\\212c0cf517282637482661905d100f-1.jpg"], "output": "商品材质", "picture2text": ""},
{"id": "210791c817279958919221102d0a98", "image": ["E:\\天池比赛\\tianchi\\train\\images\\210791c817279958919221102d0a98-0.jpg", "E:\\天池比赛\\tianchi\\train\\images\\210791c817279958919221102d0a98-1.jpg"], "output": "反馈密封性不好", "picture2text": ""},
{"id": "21074c8a17280904714122520d0a4b", "image": ["E:\\天池比赛\\tianchi\\train\\images\\21074c8a17280904714122520d0a4b-0.jpg"], "output": "功效功能", "picture2text": ""},
{"id": "21336cf817279476291755440d1000", "image": ["E:\\天池比赛\\tianchi\\train\\images\\21336cf817279476291755440d1000-0.jpg"], "output": "单品推荐", "picture2text": ""},
{"id": "2150996617273508585372019d0fac", "image": ["E:\\天池比赛\\tianchi\\train\\images\\2150996617273508585372019d0fac-0.jpg"], "output": "是否好用", "picture2text": ""},
{"id": "0b5decd817280205317264132d0b55", "image": ["E:\\天池比赛\\tianchi\\train\\images\\0b5decd817280205317264132d0b55-0.jpg"], "output": "能否调光", "picture2text": ""},
{"id": "213d2ff717273968329473175d0fd1", "image": ["E:\\天池比赛\\tianchi\\train\\images\\213d2ff717273968329473175d0fd1-0.jpg"], "output": "用法用量", "picture2text": ""},
{"id": "213dfe7817272442956787016d0f74", "image": ["E:\\天池比赛\\tianchi\\train\\images\\213dfe7817272442956787016d0f74-0.jpg"], "output": "版本款型区别", "picture2text": ""},
{"id": "2106c60d17277896007507628d101f", "image": ["E:\\天池比赛\\tianchi\\train\\images\\2106c60d17277896007507628d101f-0.jpg"], "output": "用法用量", "picture2text": ""},
{"id": "0b50e86617278322529348243d1005", "image": ["E:\\天池比赛\\tianchi\\train\\images\\0b50e86617278322529348243d1005-0.jpg"], "output": "用法用量", "picture2text": ""},
{"id": "212ca02217280908354068541d1018", "image": ["E:\\天池比赛\\tianchi\\train\\images\\212ca02217280908354068541d1018-0.jpg"], "output": "上市时间", "picture2text": ""},
{"id": "0b5102ba17275194553094576d0f9d", "image": ["E:\\天池比赛\\tianchi\\train\\images\\0b5102ba17275194553094576d0f9d-0.jpg", "E:\\天池比赛\\tianchi\\train\\images\\0b5102ba17275194553094576d0f9d-1.jpg"], "output": "商品规格", "picture2text": ""},
{"id": "212789ae17282118806051386d0fd7", "image": ["E:\\天池比赛\\tianchi\\train\\images\\212789ae17282118806051386d0fd7-0.jpg"], "output": "适用季节", "picture2text": ""},
{"id": "210571a317278881181303946d0fbc", "image": ["E:\\天池比赛\\tianchi\\train\\images\\210571a317278881181303946d0fbc-0.jpg"], "output": "信号情况", "picture2text": ""},
{"id": "2104be7517278113196275458d0fb1", "image": ["E:\\天池比赛\\tianchi\\train\\images\\2104be7517278113196275458d0fb1-0.jpg"], "output": "养护方法", "picture2text": ""},
{"id": "213373ad17282233218817488d0b2c", "image": ["E:\\天池比赛\\tianchi\\train\\images\\213373ad17282233218817488d0b2c-0.jpg"], "output": "信号情况", "picture2text": ""},
{"id": "0bb831ca17275001713458607d0ffc", "image": ["E:\\天池比赛\\tianchi\\train\\images\\0bb831ca17275001713458607d0ffc-0.jpg", "E:\\天池比赛\\tianchi\\train\\images\\0bb831ca17275001713458607d0ffc-1.jpg"], "output": "养护方法", "picture2text": ""},
{"id": "21041fd117272692716192532d0af8", "image": ["E:\\天池比赛\\tianchi\\train\\images\\21041fd117272692716192532d0af8-0.jpg"], "output": "版本款型区别", "picture2text": ""},
{"id": "212c128d17283108246927096d0b0f", "image": ["E:\\天池比赛\\tianchi\\train\\images\\212c128d17283108246927096d0b0f-0.jpg"], "output": "反馈用后症状", "picture2text": ""},
{"id": "2133d51a17278532177507112d1038", "image": ["E:\\天池比赛\\tianchi\\train\\images\\2133d51a17278532177507112d1038-0.jpg"], "output": "适用季节", "picture2text": ""},
{"id": "2146bce717280105706232601d1039", "image": ["E:\\天池比赛\\tianchi\\train\\images\\2146bce717280105706232601d1039-0.jpg"], "output": "版本款型区别", "picture2text": ""},
{"id": "0b51100717274963279655951d0f93", "image": ["E:\\天池比赛\\tianchi\\train\\images\\0b51100717274963279655951d0f93-0.jpg"], "output": "适用季节", "picture2text": ""},
{"id": "213ce7e917277531773448033d0ae7", "image": ["E:\\天池比赛\\tianchi\\train\\images\\213ce7e917277531773448033d0ae7-0.jpg"], "output": "套装推荐", "picture2text": ""},
{"id": "213ff08117283082204847586d0b14", "image": ["E:\\天池比赛\\tianchi\\train\\images\\213ff08117283082204847586d0b14-0.jpg"], "output": "适用季节", "picture2text": ""},
{"id": "0bb831ca17275200691155626d0ffc", "image": ["E:\\天池比赛\\tianchi\\train\\images\\0bb831ca17275200691155626d0ffc-0.jpg"], "output": "包装区别", "picture2text": ""},
{"id": "2167760a17280538289528464d0acd", "image": ["E:\\天池比赛\\tianchi\\train\\images\\2167760a17280538289528464d0acd-0.jpg"], "output": "气泡", "picture2text": ""},
{"id": "2136743317280520055212606d0fec", "image": ["E:\\天池比赛\\tianchi\\train\\images\\2136743317280520055212606d0fec-0.jpg", "E:\\天池比赛\\tianchi\\train\\images\\2136743317280520055212606d0fec-1.jpg"], "output": "适用季节", "picture2text": ""},
{"id": "212c980117273570976387871d1026", "image": ["E:\\天池比赛\\tianchi\\train\\images\\212c980117273570976387871d1026-0.jpg"], "output": "气泡", "picture2text": ""},
{"id": "213dfdcf17277838122852734d0fb0", "image": ["E:\\天池比赛\\tianchi\\train\\images\\213dfdcf17277838122852734d0fb0-0.jpg"], "output": "商品材质", "picture2text": ""},
{"id": "2166d27617273661444096305d1026", "image": ["E:\\天池比赛\\tianchi\\train\\images\\2166d27617273661444096305d1026-0.jpg", "E:\\天池比赛\\tianchi\\train\\images\\2166d27617273661444096305d1026-1.jpg"], "output": "版本款型区别", "picture2text": ""},
{"id": "0bf8fbfd17277183295445449d0ad8", "image": ["E:\\天池比赛\\tianchi\\train\\images\\0bf8fbfd17277183295445449d0ad8-0.jpg"], "output": "用法用量", "picture2text": ""},
{"id": "213ee7f117277822501582900d0fee", "image": ["E:\\天池比赛\\tianchi\\train\\images\\213ee7f117277822501582900d0fee-0.jpg"], "output": "控制方式", "picture2text": ""},
{"id": "212cb60217282990910903795d100d", "image": ["E:\\天池比赛\\tianchi\\train\\images\\212cb60217282990910903795d100d-0.jpg"], "output": "排水方式", "picture2text": ""},
{"id": "213624b017275391207356390d0fec", "image": ["E:\\天池比赛\\tianchi\\train\\images\\213624b017275391207356390d0fec-0.jpg", "E:\\天池比赛\\tianchi\\train\\images\\213624b017275391207356390d0fec-1.jpg"], "output": "气泡", "picture2text": ""},
{"id": "213cb64417274015946137647d0ae8", "image": ["E:\\天池比赛\\tianchi\\train\\images\\213cb64417274015946137647d0ae8-0.jpg"], "output": "反馈密封性不好", "picture2text": ""},
{"id": "213f98ba17282734138868767d0fce", "image": ["E:\\天池比赛\\tianchi\\train\\images\\213f98ba17282734138868767d0fce-0.jpg"], "output": "功效功能", "picture2text": ""},
{"id": "21661eea17280565202517751d0b08", "image": ["E:\\天池比赛\\tianchi\\train\\images\\21661eea17280565202517751d0b08-0.jpg", "E:\\天池比赛\\tianchi\\train\\images\\21661eea17280565202517751d0b08-1.jpg", "E:\\天池比赛\\tianchi\\train\\images\\21661eea17280565202517751d0b08-2.jpg"], "output": "套装推荐", "picture2text": ""},
{"id": "212b43ed17278687822228898d0b42", "image": ["E:\\天池比赛\\tianchi\\train\\images\\212b43ed17278687822228898d0b42-0.jpg"], "output": "商品材质", "picture2text": ""},
{"id": "212174dd17276786708028434d0ad3", "image": ["E:\\天池比赛\\tianchi\\train\\images\\212174dd17276786708028434d0ad3-0.jpg"], "output": "版本款型区别", "picture2text": ""},
{"id": "216604b817280889742573450d0fb5", "image": ["E:\\天池比赛\\tianchi\\train\\images\\216604b817280889742573450d0fb5-0.jpg"], "output": "发货数量", "picture2text": ""},
{"id": "21547af617277879036907095d0ae3", "image": ["E:\\天池比赛\\tianchi\\train\\images\\21547af617277879036907095d0ae3-0.jpg"], "output": "适用季节", "picture2text": ""},
{"id": "21662acc17272366440101709d0f58", "image": ["E:\\天池比赛\\tianchi\\train\\images\\21662acc17272366440101709d0f58-0.jpg"], "output": "包装区别", "picture2text": ""},
{"id": "21509d6617281852162998174d1036", "image": ["E:\\天池比赛\\tianchi\\train\\images\\21509d6617281852162998174d1036-0.jpg"], "output": "发货数量", "picture2text": ""},
{"id": "2132ca3717278384968496022d1002", "image": ["E:\\天池比赛\\tianchi\\train\\images\\2132ca3717278384968496022d1002-0.jpg"], "output": "适用季节", "picture2text": ""},
{"id": "2106e15717274125283528102d100d", "image": ["E:\\天池比赛\\tianchi\\train\\images\\2106e15717274125283528102d100d-0.jpg"], "output": "上市时间", "picture2text": ""},
{"id": "213febf317275261894201478d0faa", "image": ["E:\\天池比赛\\tianchi\\train\\images\\213febf317275261894201478d0faa-0.jpg"], "output": "包装区别", "picture2text": ""},
{"id": "212ba63617275795069558601d101c", "image": ["E:\\天池比赛\\tianchi\\train\\images\\212ba63617275795069558601d101c-0.jpg"], "output": "单品推荐", "picture2text": ""},
{"id": "213f613f17278283459901093d0af0", "image": ["E:\\天池比赛\\tianchi\\train\\images\\213f613f17278283459901093d0af0-0.jpg"], "output": "是否会生锈", "picture2text": ""},
{"id": "2108164117280171928032777d1033", "image": ["E:\\天池比赛\\tianchi\\train\\images\\2108164117280171928032777d1033-0.jpg", "E:\\天池比赛\\tianchi\\train\\images\\2108164117280171928032777d1033-1.jpg"], "output": "版本款型区别", "picture2text": ""},
{"id": "0bf8d95117282601737247238d0f7b", "image": ["E:\\天池比赛\\tianchi\\train\\images\\0bf8d95117282601737247238d0f7b-0.jpg"], "output": "排水方式", "picture2text": ""},
{"id": "213dcd7917275836808763010d0ae5", "image": ["E:\\天池比赛\\tianchi\\train\\images\\213dcd7917275836808763010d0ae5-0.jpg", "E:\\天池比赛\\tianchi\\train\\images\\213dcd7917275836808763010d0ae5-1.jpg"], "output": "版本款型区别", "picture2text": ""},
{"id": "212a922f17272208450908380d0ae5", "image": ["E:\\天池比赛\\tianchi\\train\\images\\212a922f17272208450908380d0ae5-0.jpg"], "output": "适用季节", "picture2text": ""},
{"id": "2107410117281887539942994d0b12", "image": ["E:\\天池比赛\\tianchi\\train\\images\\2107410117281887539942994d0b12-0.jpg"], "output": "单品推荐", "picture2text": ""},
{"id": "0b52068817282964736633091d0ad0", "image": ["E:\\天池比赛\\tianchi\\train\\images\\0b52068817282964736633091d0ad0-0.jpg"], "output": "控制方式", "picture2text": ""},
{"id": "2146a74017278574465532965d1020", "image": ["E:\\天池比赛\\tianchi\\train\\images\\2146a74017278574465532965d1020-0.jpg"], "output": "适用季节", "picture2text": ""},
{"id": "2150803017274405394913948d1007", "image": ["E:\\天池比赛\\tianchi\\train\\images\\2150803017274405394913948d1007-0.jpg"], "output": "用法用量", "picture2text": ""},
{"id": "0b52090217282960000927920d0b32", "image": ["E:\\天池比赛\\tianchi\\train\\images\\0b52090217282960000927920d0b32-0.jpg", "E:\\天池比赛\\tianchi\\train\\images\\0b52090217282960000927920d0b32-1.jpg"], "output": "套装推荐", "picture2text": ""},
{"id": "213dfdcf17276780483962930d0fb0", "image": ["E:\\天池比赛\\tianchi\\train\\images\\213dfdcf17276780483962930d0fb0-0.jpg"], "output": "商品规格", "picture2text": ""},
{"id": "213d275e17277702461966736d1015", "image": ["E:\\天池比赛\\tianchi\\train\\images\\213d275e17277702461966736d1015-0.jpg", "E:\\天池比赛\\tianchi\\train\\images\\213d275e17277702461966736d1015-1.jpg"], "output": "版本款型区别", "picture2text": ""},
{"id": "21672f4217276097961047952d0ad6", "image": ["E:\\天池比赛\\tianchi\\train\\images\\21672f4217276097961047952d0ad6-0.jpg"], "output": "气泡", "picture2text": ""},
{"id": "216627cf17277915377313917d0feb", "image": ["E:\\天池比赛\\tianchi\\train\\images\\216627cf17277915377313917d0feb-0.jpg"], "output": "用法用量", "picture2text": ""},
{"id": "2167646217282967774306725d0ffd", "image": ["E:\\天池比赛\\tianchi\\train\\images\\2167646217282967774306725d0ffd-0.jpg"], "output": "信号情况", "picture2text": ""},
{"id": "0bf8f96717276748456298594d0af1", "image": ["E:\\天池比赛\\tianchi\\train\\images\\0bf8f96717276748456298594d0af1-0.jpg"], "output": "商品规格", "picture2text": ""},
{"id": "213d261417281900576101162d0ae4", "image": ["E:\\天池比赛\\tianchi\\train\\images\\213d261417281900576101162d0ae4-0.jpg"], "output": "反馈密封性不好", "picture2text": ""},
{"id": "213df5d417275771673443131d0ff8", "image": ["E:\\天池比赛\\tianchi\\train\\images\\213df5d417275771673443131d0ff8-0.jpg"], "output": "何时上货", "picture2text": ""},
{"id": "2107ffd717282577597681789d0f82", "image": ["E:\\天池比赛\\tianchi\\train\\images\\2107ffd717282577597681789d0f82-0.jpg", "E:\\天池比赛\\tianchi\\train\\images\\2107ffd717282577597681789d0f82-1.jpg"], "output": "版本款型区别", "picture2text": ""},
{"id": "212cb60217278780574351355d100d", "image": ["E:\\天池比赛\\tianchi\\train\\images\\212cb60217278780574351355d100d-0.jpg"], "output": "控制方式", "picture2text": ""},
{"id": "0b51de5e17282962721241560d0ffb", "image": ["E:\\天池比赛\\tianchi\\train\\images\\0b51de5e17282962721241560d0ffb-0.jpg"], "output": "能否调光", "picture2text": ""},
{"id": "212cbdec17279733899781834d0f88", "image": ["E:\\天池比赛\\tianchi\\train\\images\\212cbdec17279733899781834d0f88-0.jpg"], "output": "是否会生锈", "picture2text": ""},
{"id": "2108af3917282962987777439d10c4", "image": ["E:\\天池比赛\\tianchi\\train\\images\\2108af3917282962987777439d10c4-0.jpg"], "output": "能否调光", "picture2text": ""},
{"id": "0b5138be17277008191081224d0fff", "image": ["E:\\天池比赛\\tianchi\\train\\images\\0b5138be17277008191081224d0fff-0.jpg"], "output": "商品材质", "picture2text": ""},
{"id": "21336cf817273220435878304d1000", "image": ["E:\\天池比赛\\tianchi\\train\\images\\21336cf817273220435878304d1000-0.jpg"], "output": "包装区别", "picture2text": ""},
{"id": "2107e6f317275936411822527d0ffd", "image": ["E:\\天池比赛\\tianchi\\train\\images\\2107e6f317275936411822527d0ffd-0.jpg"], "output": "商品材质", "picture2text": ""},
{"id": "21547e6f17275698208415653d0b0f", "image": ["E:\\天池比赛\\tianchi\\train\\images\\21547e6f17275698208415653d0b0f-0.jpg"], "output": "是否会生锈", "picture2text": ""},
{"id": "212a9ace17274618777305233d0b47", "image": ["E:\\天池比赛\\tianchi\\train\\images\\212a9ace17274618777305233d0b47-0.jpg"], "output": "养护方法", "picture2text": ""},
{"id": "0b50fb1817278501498316793d0ffd", "image": ["E:\\天池比赛\\tianchi\\train\\images\\0b50fb1817278501498316793d0ffd-0.jpg"], "output": "用法用量", "picture2text": ""},
{"id": "21329d2417276599524107646d0fc5", "image": ["E:\\天池比赛\\tianchi\\train\\images\\21329d2417276599524107646d0fc5-0.jpg"], "output": "适用季节", "picture2text": ""},
{"id": "21674c6817274304816502529d0b15", "image": ["E:\\天池比赛\\tianchi\\train\\images\\21674c6817274304816502529d0b15-0.jpg"], "output": "气泡", "picture2text": ""},
{"id": "2150b9fc17274905945928865d0f91", "image": ["E:\\天池比赛\\tianchi\\train\\images\\2150b9fc17274905945928865d0f91-0.jpg"], "output": "商品规格", "picture2text": ""},
{"id": "213eaad317272386605263503d0b0c", "image": ["E:\\天池比赛\\tianchi\\train\\images\\213eaad317272386605263503d0b0c-0.jpg"], "output": "商品规格", "picture2text": ""},
{"id": "0bf8ecdd17278417984286655d0fbf", "image": ["E:\\天池比赛\\tianchi\\train\\images\\0bf8ecdd17278417984286655d0fbf-0.jpg"], "output": "商品材质", "picture2text": ""},
{"id": "2107a90717278400876333538d1033", "image": ["E:\\天池比赛\\tianchi\\train\\images\\2107a90717278400876333538d1033-0.jpg"], "output": "包装区别", "picture2text": ""},
{"id": "2106c60d17280514545784450d101f", "image": ["E:\\天池比赛\\tianchi\\train\\images\\2106c60d17280514545784450d101f-0.jpg", "E:\\天池比赛\\tianchi\\train\\images\\2106c60d17280514545784450d101f-1.jpg"], "output": "何时上货", "picture2text": ""},
{"id": "210402f617273276565168251d0af2", "image": ["E:\\天池比赛\\tianchi\\train\\images\\210402f617273276565168251d0af2-0.jpg"], "output": "发货数量", "picture2text": ""},
{"id": "213ca3f617272237777542707d101d", "image": ["E:\\天池比赛\\tianchi\\train\\images\\213ca3f617272237777542707d101d-0.jpg"], "output": "排水方式", "picture2text": ""},
{"id": "2150b82817277106302952953d0a2f", "image": ["E:\\天池比赛\\tianchi\\train\\images\\2150b82817277106302952953d0a2f-0.png"], "output": "何时上货", "picture2text": ""},
{"id": "213c7f8217273090696243542d0f72", "image": ["E:\\天池比赛\\tianchi\\train\\images\\213c7f8217273090696243542d0f72-0.jpg"], "output": "反馈密封性不好", "picture2text": ""},
{"id": "213f4d8317274250410304523d03c2", "image": ["E:\\天池比赛\\tianchi\\train\\images\\213f4d8317274250410304523d03c2-0.png", "E:\\天池比赛\\tianchi\\train\\images\\213f4d8317274250410304523d03c2-1.png"], "output": "能否调光", "picture2text": ""},
{"id": "212b59eb17272698103067741d0fe8", "image": ["E:\\天池比赛\\tianchi\\train\\images\\212b59eb17272698103067741d0fe8-0.jpg"], "output": "养护方法", "picture2text": ""},
{"id": "213f676017279391314087727d0fcb", "image": ["E:\\天池比赛\\tianchi\\train\\images\\213f676017279391314087727d0fcb-0.jpg", "E:\\天池比赛\\tianchi\\train\\images\\213f676017279391314087727d0fcb-1.jpg"], "output": "版本款型区别", "picture2text": ""},
{"id": "2132e16417283138179593229d0a7e", "image": ["E:\\天池比赛\\tianchi\\train\\images\\2132e16417283138179593229d0a7e-0.jpg"], "output": "单品推荐", "picture2text": ""},
{"id": "213fa0ea17281899571935301d1002", "image": ["E:\\天池比赛\\tianchi\\train\\images\\213fa0ea17281899571935301d1002-0.jpg", "E:\\天池比赛\\tianchi\\train\\images\\213fa0ea17281899571935301d1002-1.jpg"], "output": "商品材质", "picture2text": ""},
{"id": "2150a00417272609496387026d0ff2", "image": ["E:\\天池比赛\\tianchi\\train\\images\\2150a00417272609496387026d0ff2-0.jpg"], "output": "包装区别", "picture2text": ""},
{"id": "21328e1617274933237681904d0fc2", "image": ["E:\\天池比赛\\tianchi\\train\\images\\21328e1617274933237681904d0fc2-0.jpg"], "output": "单品推荐", "picture2text": ""},
{"id": "21077c3717280986384556547d0ffc", "image": ["E:\\天池比赛\\tianchi\\train\\images\\21077c3717280986384556547d0ffc-0.jpg"], "output": "上市时间", "picture2text": ""},
{"id": "213ef6a617273607777854871d0b7c", "image": ["E:\\天池比赛\\tianchi\\train\\images\\213ef6a617273607777854871d0b7c-0.jpg"], "output": "套装推荐", "picture2text": ""},
{"id": "2107a8e317280376285661362d14d6", "image": ["E:\\天池比赛\\tianchi\\train\\images\\2107a8e317280376285661362d14d6-0.jpg"], "output": "是否易褪色", "picture2text": ""},
{"id": "2150ac5517273424710348239d1048", "image": ["E:\\天池比赛\\tianchi\\train\\images\\2150ac5517273424710348239d1048-0.jpg"], "output": "能否调光", "picture2text": ""},
{"id": "210767a617278675393267649d1040", "image": ["E:\\天池比赛\\tianchi\\train\\images\\210767a617278675393267649d1040-0.jpg"], "output": "版本款型区别", "picture2text": ""},
{"id": "213e5b6717280386556962296d1006", "image": ["E:\\天池比赛\\tianchi\\train\\images\\213e5b6717280386556962296d1006-0.jpg", "E:\\天池比赛\\tianchi\\train\\images\\213e5b6717280386556962296d1006-1.jpg"], "output": "能否调光", "picture2text": ""},
{"id": "216718e917279171895241132d0b0b", "image": ["E:\\天池比赛\\tianchi\\train\\images\\216718e917279171895241132d0b0b-0.jpg"], "output": "功效功能", "picture2text": ""},
{"id": "213e87c017275846911103217d0fd5", "image": ["E:\\天池比赛\\tianchi\\train\\images\\213e87c017275846911103217d0fd5-0.jpg"], "output": "上市时间", "picture2text": ""},
{"id": "2107bb1017279214296645020d0f68", "image": ["E:\\天池比赛\\tianchi\\train\\images\\2107bb1017279214296645020d0f68-0.jpg"], "output": "养护方法", "picture2text": ""},
{"id": "213cd4ed17280105088072492d1014", "image": ["E:\\天池比赛\\tianchi\\train\\images\\213cd4ed17280105088072492d1014-0.jpg"], "output": "包装区别", "picture2text": ""},
{"id": "21328e1617278676382286919d0fc2", "image": ["E:\\天池比赛\\tianchi\\train\\images\\21328e1617278676382286919d0fc2-0.jpg"], "output": "商品材质", "picture2text": ""},
{"id": "21663d6817282073815363902d0af5", "image": ["E:\\天池比赛\\tianchi\\train\\images\\21663d6817282073815363902d0af5-0.jpg"], "output": "版本款型区别", "picture2text": ""},
{"id": "213c79b617283023834961475d0fce", "image": ["E:\\天池比赛\\tianchi\\train\\images\\213c79b617283023834961475d0fce-0.jpg"], "output": "包装区别", "picture2text": ""},
{"id": "2106cf0a17280320521956109d104f", "image": ["E:\\天池比赛\\tianchi\\train\\images\\2106cf0a17280320521956109d104f-0.jpg"], "output": "单品推荐", "picture2text": ""},
{"id": "0b51423417281892477488104d0ad2", "image": ["E:\\天池比赛\\tianchi\\train\\images\\0b51423417281892477488104d0ad2-0.jpg"], "output": "单品推荐", "picture2text": ""},
{"id": "2103ef2017277513299437368d102f", "image": ["E:\\天池比赛\\tianchi\\train\\images\\2103ef2017277513299437368d102f-0.jpg"], "output": "养护方法", "picture2text": ""},
{"id": "213cd4d017272439832181329d0fa8", "image": ["E:\\天池比赛\\tianchi\\train\\images\\213cd4d017272439832181329d0fa8-0.jpg"], "output": "能否调光", "picture2text": ""},
{"id": "210811f817277416898123956d0ae9", "image": ["E:\\天池比赛\\tianchi\\train\\images\\210811f817277416898123956d0ae9-0.jpg"], "output": "能否调光", "picture2text": ""},
{"id": "0b1fecf117281996029976346d1433", "image": ["E:\\天池比赛\\tianchi\\train\\images\\0b1fecf117281996029976346d1433-0.jpg"], "output": "反馈密封性不好", "picture2text": ""},
{"id": "216715cd17278240446705339d103e", "image": ["E:\\天池比赛\\tianchi\\train\\images\\216715cd17278240446705339d103e-0.jpg"], "output": "单品推荐", "picture2text": ""},
{"id": "210475c617280231013845576d0fca", "image": ["E:\\天池比赛\\tianchi\\train\\images\\210475c617280231013845576d0fca-0.jpg"], "output": "发货数量", "picture2text": ""},
{"id": "213e87c017273184139862170d0fd5", "image": ["E:\\天池比赛\\tianchi\\train\\images\\213e87c017273184139862170d0fd5-0.jpg"], "output": "套装推荐", "picture2text": ""},
{"id": "0bf8ed6517276564228503329d100d", "image": ["E:\\天池比赛\\tianchi\\train\\images\\0bf8ed6517276564228503329d100d-0.jpg"], "output": "何时上货", "picture2text": ""},
{"id": "3fc85b30-3ab3-4cad-a2de-324e2ae6a078-1279", "image": ["E:\\天池比赛\\tianchi\\train\\images\\3fc85b30-3ab3-4cad-a2de-324e2ae6a078-1279-0.jpg"], "output": "退货页面", "picture2text": "这是一张退货申请页面的截图，显示商家已同意退货，并提示用户支付退货运费后才能使用在线寄件服务。商品为粉色草莓熊三件套全车坐垫。"},
{"id": "19c1964c-5f1b-41b3-98fe-405a987e9358-8", "image": ["E:\\天池比赛\\tianchi\\train\\images\\19c1964c-5f1b-41b3-98fe-405a987e9358-8-0.jpg"], "output": "实物拍摄(含售后)", "picture2text": "图片展示了几株植物，根部包裹着苔藓，放置在一个打开的纸箱中。"},
{"id": "6f59b27a-2321-45aa-b0f3-b245d19d1883-1591", "image": ["E:\\天池比赛\\tianchi\\train\\images\\6f59b27a-2321-45aa-b0f3-b245d19d1883-1591-0.jpg"], "output": "店铺页面", "picture2text": "这是一张展示VO品牌服务承诺和新国标可上牌电动车的手机应用界面截图。\n\n- VO品牌服务承诺包括：正规发票、售后一对一服务、闪电发货、分期免息、终身售后、7天无理由退货、原装正品、价保30天。\n- 新国标可上牌电动车的标志。"},
{"id": "e7a3565c-a077-4497-8b23-707ae7d16236-1517", "image": ["E:\\天池比赛\\tianchi\\train\\images\\e7a3565c-a077-4497-8b23-707ae7d16236-1517-0.jpg"], "output": "店铺页面", "picture2text": "这是一张展示家居商品的电商平台页面截图。\n\n- 北美进口FAS级木料沙发椅，原价3891.2元，券后价3771.2元，已有100+人付款。\n- 本店懒人沙发热销第1名，原价1343.2元，折后价100+人付款。\n- 本店沙发椅热销第1名，原价791.2元，折后价100+人付款，3期免息。\n- 解压小陀螺，价格19.9元，已有3000+人付款。"},
{"id": "fac5b276-8b3f-48c3-af74-3d83b2a1535f-621", "image": ["E:\\天池比赛\\tianchi\\train\\images\\fac5b276-8b3f-48c3-af74-3d83b2a1535f-621-0.jpg"], "output": "支付页面", "picture2text": "这是一张显示运费支付页面的截图。\n\n- 基础运费：32.20元\n- 计费类型：按重量计费\n- 计费重量：5.00kg\n- 首重价格：10.20元（1kg内价格）\n- 运费险：暂不可用\n- 选择优惠：暂无优惠券可用\n- 实际支付：¥32.20"},
{"id": "8971fd49-81b7-4a0d-898d-99c6e64ab21a-1776", "image": ["E:\\天池比赛\\tianchi\\train\\images\\8971fd49-81b7-4a0d-898d-99c6e64ab21a-1776-0.jpg"], "output": "优惠券领取页面", "picture2text": "这是一张显示订单确认页面的截图，商品总价为600元，官方立减104元，优惠详情中有一个88VIP专享天天红包，可减2元。"},
{"id": "f13dd085-9ee4-495a-ba91-bda94eedbb85-1051", "image": ["E:\\天池比赛\\tianchi\\train\\images\\f13dd085-9ee4-495a-ba91-bda94eedbb85-1051-0.jpg"], "output": "物流页面-物流异常页面", "picture2text": "这是一张显示物流异常提醒的订单详情页面截图。\n\n- 物流异常提醒：5月23日13:43，快件比预计到达时间有所延迟，商家已补发。\n- 订单商品：黑色26码凉鞋，价格45元，支持7天无理由退换。\n- 当前包裹位置：台州市。"},
{"id": "78ed06ab-8489-4783-9153-01a15e72661f-338", "image": ["E:\\天池比赛\\tianchi\\train\\images\\78ed06ab-8489-4783-9153-01a15e72661f-338-0.jpg"], "output": "商品详情页截图", "picture2text": "这是一张展示电商平台退货政策的截图。\n\n- 退货运费险：商家赠送运费险，退换货选择上门取件自动减免首重运费；若选择自寄，参照首重标准赔付，具体以“订单详情-退货运费险”页面为准。\n- 7天无理由退货：满足7天无理由退货申请的前提下，包邮商品需要买家承担退货运费，非包邮商品需要买家承担发货和退货运费。"},
{"id": "fde410ef-7597-4eee-8ad1-15a9903446db-2031", "image": ["E:\\天池比赛\\tianchi\\train\\images\\fde410ef-7597-4eee-8ad1-15a9903446db-2031-0.jpg"], "output": "投诉举报页面", "picture2text": "这是一张关于消费者在电商平台投诉卖家虚假发货的进度详情截图。\n\n- 投诉原因：发货物流问题/虚假发货\n- 投诉说明：不是一个东西\n- 商品信息：颜色分类为白桔-高端版本鞋，鞋码41.5，价格226.89元\n- 投诉状态：已撤销投诉（06-06 16:29）\n- 卖家处理中（06-05 17:42）\n- 消费者发起投诉（06-05 17:42"}
]